agios/__init__.py
agios/evolution.py
agios/extras.py
agios-2017.7.1.dist-info/DESCRIPTION.rst
agios-2017.7.1.dist-info/METADATA
agios-2017.7.1.dist-info/RECORD
agios-2017.7.1.dist-info/WHEEL
agios-2017.7.1.dist-info/metadata.json
agios-2017.7.1.dist-info/top_level.txt
