Metadata-Version: 2.0
Name: agios
Version: 2017.7.1
Summary: Simple genetic algorithms framework for Python
Home-page: https://github.com/mkorman9/agios
Author: Michal Korman
Author-email: m.korman94@gmail.com
License: MIT
Download-URL: https://github.com/mkorman9/agios/tarball/2017.7.1
Keywords: ai genetic algorithms
Platform: UNKNOWN
Classifier: Topic :: Scientific/Engineering :: Artificial Intelligence
Classifier: Programming Language :: Python :: 3
Requires-Dist: Pillow
Requires-Dist: numpy
